fix_winpath.py
fix_winpath-0.0.1.dist-info/LICENSE
fix_winpath-0.0.1.dist-info/METADATA
fix_winpath-0.0.1.dist-info/WHEEL
fix_winpath-0.0.1.dist-info/top_level.txt
fix_winpath-0.0.1.dist-info/RECORD
