Metadata-Version: 2.1
Name: fix-winpath
Version: 0.0.1
Summary: Fixes windows PATH environment variable to find python.exe, pip.exe and more
Home-page: https://github.com/nonZero/fix-winpath
Author: Udi Oron
Author-email: udioron@gmail.com
License: UNKNOWN
Platform: UNKNOWN
Classifier: Programming Language :: Python :: 3
Classifier: License :: Public Domain
Classifier: Operating System :: Microsoft :: Windows
